jutge/monitor/monitor.py
jutge_monitor-1.0.0.dist-info/LICENSE
jutge_monitor-1.0.0.dist-info/METADATA
jutge_monitor-1.0.0.dist-info/WHEEL
jutge_monitor-1.0.0.dist-info/entry_points.txt
jutge_monitor-1.0.0.dist-info/top_level.txt
jutge_monitor-1.0.0.dist-info/RECORD
