Metadata-Version: 2.1
Name: jutge-monitor
Version: 1.0.0
Summary: Monitor for worker machines of Jutge.org
Home-page: https://github.com/jutge-org/jutge-monitor
Author: Jordi Petit et al
Author-email: jpetit@cs.upc.edu
License: Apache
Download-URL: https://github.com/jutge-org/jutge-monitor/tarball/1.0.0
Keywords: jutge,jutge.org,monitor
Platform: UNKNOWN
Classifier: Development Status :: 5 - Production/Stable
Classifier: Environment :: Console
Classifier: Intended Audience :: Education
Classifier: License :: OSI Approved :: Apache Software License
Classifier: Operating System :: OS Independent
Classifier: Programming Language :: Python
Classifier: Programming Language :: Python :: 3
Classifier: Programming Language :: Python :: 3.5
Classifier: Programming Language :: Python :: 3.6
Classifier: Programming Language :: Python :: 3.7
Classifier: Topic :: Education
Requires-Dist: pyyaml (>=5.1)
Requires-Dist: uptime
Requires-Dist: psutil
Requires-Dist: py-cpuinfo
Requires-Dist: jsons
